nose2_spark/__init__.py
nose2_spark-0.3.dist-info/DESCRIPTION.rst
nose2_spark-0.3.dist-info/METADATA
nose2_spark-0.3.dist-info/RECORD
nose2_spark-0.3.dist-info/WHEEL
nose2_spark-0.3.dist-info/metadata.json
nose2_spark-0.3.dist-info/top_level.txt
