Metadata-Version: 2.0
Name: nose2-spark
Version: 0.3
Summary: nose2 plugin to run the tests with support of pyspark.
Home-page: https://github.com/malexer/nose2-spark
Author: Alex (Oleksii) Markov
Author-email: alex@markovs.me
License: MIT
Keywords: nose2 spark pyspark unittest test
Platform: UNKNOWN
Classifier: Development Status :: 4 - Beta
Classifier: Intended Audience :: Developers
Classifier: Intended Audience :: Science/Research
Classifier: Topic :: Software Development :: Libraries :: Python Modules
Classifier: License :: OSI Approved :: MIT License
Classifier: Programming Language :: Python :: 2
Classifier: Programming Language :: Python :: 2.7
Classifier: Programming Language :: Python :: 3
Classifier: Programming Language :: Python :: 3.2
Classifier: Programming Language :: Python :: 3.3
Classifier: Programming Language :: Python :: 3.4
Classifier: Programming Language :: Python :: 3.5
Classifier: Programming Language :: Python :: 3.6
Classifier: Topic :: Software Development :: Testing
Requires-Dist: findspark
Requires-Dist: nose2
